django_migration_checks/__init__.py
django_migration_checks/apps.py
django_migration_checks/checks.py
django_migration_checks/exceptions.py
django_migration_checks/handler.py
django_migration_checks/logging.py
django_migration_checks/messages.py
django_migration_checks/settings.py
django_migration_checks/types.py
django_migration_checks-0.1.1.dist-info/LICENSE
django_migration_checks-0.1.1.dist-info/METADATA
django_migration_checks-0.1.1.dist-info/WHEEL
django_migration_checks-0.1.1.dist-info/RECORD
